bullet_dodger/__init__.py
bullet_dodger/bullet_dodger.py
bullet_dodger/assets/Hitman.ogg
bullet_dodger/assets/bullet.png
bullet_dodger/assets/ground.png
bullet_dodger/assets/gun_fire.ogg
bullet_dodger/locale/build.py
bullet_dodger/locale/de.po
bullet_dodger/locale/en.po
bullet_dodger/locale/eo.mo
bullet_dodger/locale/eo.po
bullet_dodger/locale/es.po
bullet_dodger/locale/pt.po
bullet_dodger/locale/de/LC_MESSAGES/bullet_dodger.mo
bullet_dodger/locale/en/LC_MESSAGES/bullet_dodger.mo
bullet_dodger/locale/eo/LC_MESSAGES/bullet_dodger.mo
bullet_dodger/locale/es/LC_MESSAGES/bullet_dodger.mo
bullet_dodger/locale/pt/LC_MESSAGES/bullet_dodger.mo
bullet_dodger-2.1.4.dist-info/LICENSE
bullet_dodger-2.1.4.dist-info/METADATA
bullet_dodger-2.1.4.dist-info/WHEEL
bullet_dodger-2.1.4.dist-info/entry_points.txt
bullet_dodger-2.1.4.dist-info/top_level.txt
bullet_dodger-2.1.4.dist-info/RECORD
